{
  "version": 1.0,
  "grid_size": 96,
  "tabs": [
    {
      "name": "Teleoperated",
      "grid_layout": {
        "layouts": [],
        "containers": [
          {
            "title": "Motor Speed",
            "x": 480.0,
            "y": 96.0,
            "width": 96.0,
            "height": 96.0,
            "type": "Text Display",
            "properties": {
              "topic": "/SmartDashboard/Motor Speed",
              "period": 0.06,
              "data_type": "double",
              "show_submit_button": false
            }
          },
          {
            "title": "Test Timer",
            "x": 480.0,
            "y": 288.0,
            "width": 96.0,
            "height": 96.0,
            "type": "Text Display",
            "properties": {
              "topic": "/SmartDashboard/Test Timer",
              "period": 0.06,
              "data_type": "double",
              "show_submit_button": false
            }
          },
          {
            "title": "Test button",
            "x": 672.0,
            "y": 96.0,
            "width": 96.0,
            "height": 96.0,
            "type": "Boolean Box",
            "properties": {
              "topic": "/SmartDashboard/Test button",
              "period": 0.06,
              "data_type": "boolean",
              "true_color": 4283215696,
              "false_color": 4294198070,
              "true_icon": "None",
              "false_icon": "None"
            }
          }
        ]
      }
    },
    {
      "name": "Autonomous",
      "grid_layout": {
        "layouts": [],
        "containers": []
      }
    },
    {
      "name": "Tab 3",
      "grid_layout": {
        "layouts": [
          {
            "title": "List Layout",
            "x": 1248.0,
            "y": 0.0,
            "width": 288.0,
            "height": 480.0,
            "type": "List Layout",
            "properties": {
              "label_position": "TOP"
            },
            "children": [
              {
                "title": "# Top Triangle",
                "x": 256.0,
                "y": 128.0,
                "width": 128.0,
                "height": 128.0,
                "type": "Boolean Box",
                "properties": {
                  "topic": "/SmartDashboard/# Top Triangle",
                  "period": 0.06,
                  "data_type": "boolean",
                  "true_color": 4283215696,
                  "false_color": 4294198070,
                  "true_icon": "None",
                  "false_icon": "None"
                }
              },
              {
                "title": "# Reef Level",
                "x": 256.0,
                "y": 256.0,
                "width": 128.0,
                "height": 128.0,
                "type": "Text Display",
                "properties": {
                  "topic": "/SmartDashboard/# Reef Level",
                  "period": 0.06,
                  "data_type": "string",
                  "show_submit_button": false
                }
              },
              {
                "title": "# Targeting Net",
                "x": 256.0,
                "y": 256.0,
                "width": 128.0,
                "height": 128.0,
                "type": "Boolean Box",
                "properties": {
                  "topic": "/SmartDashboard/# Targeting Net",
                  "period": 0.06,
                  "data_type": "boolean",
                  "true_color": 4283215696,
                  "false_color": 4294198070,
                  "true_icon": "None",
                  "false_icon": "None"
                }
              },
              {
                "title": "# Algae Pickup",
                "x": 256.0,
                "y": 384.0,
                "width": 128.0,
                "height": 128.0,
                "type": "Boolean Box",
                "properties": {
                  "topic": "/SmartDashboard/# Algae Pickup",
                  "period": 0.06,
                  "data_type": "boolean",
                  "true_color": 4283215696,
                  "false_color": 4294198070,
                  "true_icon": "None",
                  "false_icon": "None"
                }
              }
            ]
          }
        ],
        "containers": [
          {
            "title": "# Has Algae",
            "x": 1152.0,
            "y": 96.0,
            "width": 96.0,
            "height": 96.0,
            "type": "Boolean Box",
            "properties": {
              "topic": "/SmartDashboard/# Has Algae",
              "period": 0.06,
              "data_type": "boolean",
              "true_color": 4283215696,
              "false_color": 4294198070,
              "true_icon": "None",
              "false_icon": "None"
            }
          },
          {
            "title": "# Has Coral",
            "x": 1152.0,
            "y": 0.0,
            "width": 96.0,
            "height": 96.0,
            "type": "Boolean Box",
            "properties": {
              "topic": "/SmartDashboard/# Has Coral",
              "period": 0.06,
              "data_type": "boolean",
              "true_color": 4283215696,
              "false_color": 4294198070,
              "true_icon": "None",
              "false_icon": "None"
            }
          },
          {
            "title": "@ Alage Speed",
            "x": 96.0,
            "y": 0.0,
            "width": 96.0,
            "height": 96.0,
            "type": "Text Display",
            "properties": {
              "topic": "/SmartDashboard/@ Alage Speed",
              "period": 0.06,
              "data_type": "double",
              "show_submit_button": false
            }
          },
          {
            "title": "@ Arm Position",
            "x": 192.0,
            "y": 0.0,
            "width": 96.0,
            "height": 96.0,
            "type": "Text Display",
            "properties": {
              "topic": "/SmartDashboard/@ Arm Position",
              "period": 0.06,
              "data_type": "double",
              "show_submit_button": false
            }
          },
          {
            "title": "@ Arm Target",
            "x": 192.0,
            "y": 96.0,
            "width": 96.0,
            "height": 96.0,
            "type": "Text Display",
            "properties": {
              "topic": "/SmartDashboard/@ Arm Target",
              "period": 0.06,
              "data_type": "double",
              "show_submit_button": false
            }
          },
          {
            "title": "@ Coral Speed",
            "x": 96.0,
            "y": 96.0,
            "width": 96.0,
            "height": 96.0,
            "type": "Text Display",
            "properties": {
              "topic": "/SmartDashboard/@ Coral Speed",
              "period": 0.06,
              "data_type": "double",
              "show_submit_button": false
            }
          },
          {
            "title": "@ Lift Position",
            "x": 288.0,
            "y": 0.0,
            "width": 96.0,
            "height": 96.0,
            "type": "Text Display",
            "properties": {
              "topic": "/SmartDashboard/@ Lift Position",
              "period": 0.06,
              "data_type": "double",
              "show_submit_button": false
            }
          },
          {
            "title": "@ Lift Target",
            "x": 288.0,
            "y": 96.0,
            "width": 96.0,
            "height": 96.0,
            "type": "Text Display",
            "properties": {
              "topic": "/SmartDashboard/@ Lift Target",
              "period": 0.06,
              "data_type": "double",
              "show_submit_button": false
            }
          },
          {
            "title": "@ Superstructure position",
            "x": 0.0,
            "y": 192.0,
            "width": 288.0,
            "height": 96.0,
            "type": "Text Display",
            "properties": {
              "topic": "/SmartDashboard/@ Superstructure position",
              "period": 0.06,
              "data_type": "string",
              "show_submit_button": false
            }
          },
          {
            "title": "Alliance Color",
            "x": 0.0,
            "y": 96.0,
            "width": 96.0,
            "height": 96.0,
            "type": "Boolean Box",
            "properties": {
              "topic": "/SmartDashboard/Alliance Color",
              "period": 0.06,
              "data_type": "boolean",
              "true_color": 4283215696,
              "false_color": 4294198070,
              "true_icon": "None",
              "false_icon": "None"
            }
          },
          {
            "title": "Gyro Reading",
            "x": 0.0,
            "y": 0.0,
            "width": 96.0,
            "height": 96.0,
            "type": "Text Display",
            "properties": {
              "topic": "/SmartDashboard/Gyro Reading",
              "period": 0.06,
              "data_type": "double",
              "show_submit_button": false
            }
          },
          {
            "title": "@ current timer",
            "x": 1056.0,
            "y": 96.0,
            "width": 96.0,
            "height": 96.0,
            "type": "Text Display",
            "properties": {
              "topic": "/SmartDashboard/@ current timer",
              "period": 0.06,
              "data_type": "double",
              "show_submit_button": false
            }
          },
          {
            "title": "@ delay timer",
            "x": 1056.0,
            "y": 0.0,
            "width": 96.0,
            "height": 96.0,
            "type": "Text Display",
            "properties": {
              "topic": "/SmartDashboard/@ delay timer",
              "period": 0.06,
              "data_type": "double",
              "show_submit_button": false
            }
          },
          {
            "title": "@ is stowed",
            "x": 1152.0,
            "y": 192.0,
            "width": 96.0,
            "height": 96.0,
            "type": "Boolean Box",
            "properties": {
              "topic": "/SmartDashboard/@ is stowed",
              "period": 0.06,
              "data_type": "boolean",
              "true_color": 4283215696,
              "false_color": 4294198070,
              "true_icon": "None",
              "false_icon": "None"
            }
          },
          {
            "title": "@ algae scoring",
            "x": 1056.0,
            "y": 288.0,
            "width": 96.0,
            "height": 96.0,
            "type": "Boolean Box",
            "properties": {
              "topic": "/SmartDashboard/@ algae scoring",
              "period": 0.06,
              "data_type": "boolean",
              "true_color": 4283215696,
              "false_color": 4294198070,
              "true_icon": "None",
              "false_icon": "None"
            }
          },
          {
            "title": "@ coral scoring",
            "x": 1056.0,
            "y": 192.0,
            "width": 96.0,
            "height": 96.0,
            "type": "Boolean Box",
            "properties": {
              "topic": "/SmartDashboard/@ coral scoring",
              "period": 0.06,
              "data_type": "boolean",
              "true_color": 4283215696,
              "false_color": 4294198070,
              "true_icon": "None",
              "false_icon": "None"
            }
          },
          {
            "title": "@ thing",
            "x": 1056.0,
            "y": 384.0,
            "width": 96.0,
            "height": 96.0,
            "type": "Boolean Box",
            "properties": {
              "topic": "/SmartDashboard/@ thing",
              "period": 0.06,
              "data_type": "boolean",
              "true_color": 4283215696,
              "false_color": 4294198070,
              "true_icon": "None",
              "false_icon": "None"
            }
          },
          {
            "title": "Odo X",
            "x": 384.0,
            "y": 0.0,
            "width": 192.0,
            "height": 192.0,
            "type": "Text Display",
            "properties": {
              "topic": "/SmartDashboard/Odo X",
              "period": 0.06,
              "data_type": "double",
              "show_submit_button": false
            }
          },
          {
            "title": "Odo Y",
            "x": 384.0,
            "y": 192.0,
            "width": 192.0,
            "height": 192.0,
            "type": "Text Display",
            "properties": {
              "topic": "/SmartDashboard/Odo Y",
              "period": 0.06,
              "data_type": "double",
              "show_submit_button": false
            }
          },
          {
            "title": "limelight-backVision x",
            "x": 576.0,
            "y": 0.0,
            "width": 192.0,
            "height": 192.0,
            "type": "Text Display",
            "properties": {
              "topic": "/SmartDashboard/limelight-backVision x",
              "period": 0.06,
              "data_type": "double",
              "show_submit_button": false
            }
          },
          {
            "title": "limelight-backVision y",
            "x": 576.0,
            "y": 192.0,
            "width": 192.0,
            "height": 192.0,
            "type": "Text Display",
            "properties": {
              "topic": "/SmartDashboard/limelight-backVision y",
              "period": 0.06,
              "data_type": "double",
              "show_submit_button": false
            }
          },
          {
            "title": "limelight-frontVision x",
            "x": 768.0,
            "y": 0.0,
            "width": 192.0,
            "height": 192.0,
            "type": "Text Display",
            "properties": {
              "topic": "/SmartDashboard/limelight-frontVision x",
              "period": 0.06,
              "data_type": "double",
              "show_submit_button": false
            }
          },
          {
            "title": "limelight-frontVision y",
            "x": 768.0,
            "y": 192.0,
            "width": 192.0,
            "height": 192.0,
            "type": "Text Display",
            "properties": {
              "topic": "/SmartDashboard/limelight-frontVision y",
              "period": 0.06,
              "data_type": "double",
              "show_submit_button": false
            }
          },
          {
            "title": "limelight-front tv",
            "x": 768.0,
            "y": 384.0,
            "width": 192.0,
            "height": 192.0,
            "type": "Boolean Box",
            "properties": {
              "topic": "/SmartDashboard/limelight-front tv",
              "period": 0.06,
              "data_type": "boolean",
              "true_color": 4283215696,
              "false_color": 4294198070,
              "true_icon": "None",
              "false_icon": "None"
            }
          },
          {
            "title": "limelight-back tv",
            "x": 576.0,
            "y": 384.0,
            "width": 192.0,
            "height": 192.0,
            "type": "Boolean Box",
            "properties": {
              "topic": "/SmartDashboard/limelight-back tv",
              "period": 0.06,
              "data_type": "boolean",
              "true_color": 4283215696,
              "false_color": 4294198070,
              "true_icon": "None",
              "false_icon": "None"
            }
          },
          {
            "title": "@ absolute arm",
            "x": 960.0,
            "y": 480.0,
            "width": 192.0,
            "height": 192.0,
            "type": "Text Display",
            "properties": {
              "topic": "/SmartDashboard/@ absolute arm",
              "period": 0.06,
              "data_type": "double",
              "show_submit_button": false
            }
          }
        ]
      }
    },
    {
      "name": "Competition",
      "grid_layout": {
        "layouts": [],
        "containers": [
          {
            "title": "# Reef L1",
            "x": 1152.0,
            "y": 288.0,
            "width": 192.0,
            "height": 96.0,
            "type": "Boolean Box",
            "properties": {
              "topic": "/SmartDashboard/# Reef L1",
              "period": 0.06,
              "data_type": "boolean",
              "true_color": 4283215696,
              "false_color": 4294198070,
              "true_icon": "None",
              "false_icon": "None"
            }
          },
          {
            "title": "# Reef L2",
            "x": 1152.0,
            "y": 192.0,
            "width": 192.0,
            "height": 96.0,
            "type": "Boolean Box",
            "properties": {
              "topic": "/SmartDashboard/# Reef L2",
              "period": 0.06,
              "data_type": "boolean",
              "true_color": 4283215696,
              "false_color": 4294198070,
              "true_icon": "None",
              "false_icon": "None"
            }
          },
          {
            "title": "# Reef L3",
            "x": 1152.0,
            "y": 96.0,
            "width": 192.0,
            "height": 96.0,
            "type": "Boolean Box",
            "properties": {
              "topic": "/SmartDashboard/# Reef L3",
              "period": 0.06,
              "data_type": "boolean",
              "true_color": 4283215696,
              "false_color": 4294198070,
              "true_icon": "None",
              "false_icon": "None"
            }
          },
          {
            "title": "# Reef L4",
            "x": 1152.0,
            "y": 0.0,
            "width": 192.0,
            "height": 96.0,
            "type": "Boolean Box",
            "properties": {
              "topic": "/SmartDashboard/# Reef L4",
              "period": 0.06,
              "data_type": "boolean",
              "true_color": 4283215696,
              "false_color": 4294198070,
              "true_icon": "None",
              "false_icon": "None"
            }
          },
          {
            "title": "# Has Algae",
            "x": 576.0,
            "y": 96.0,
            "width": 192.0,
            "height": 96.0,
            "type": "Boolean Box",
            "properties": {
              "topic": "/SmartDashboard/# Has Algae",
              "period": 0.06,
              "data_type": "boolean",
              "true_color": 4282698453,
              "false_color": 4294198070,
              "true_icon": "None",
              "false_icon": "X"
            }
          },
          {
            "title": "# Has Coral",
            "x": 576.0,
            "y": 0.0,
            "width": 192.0,
            "height": 96.0,
            "type": "Boolean Box",
            "properties": {
              "topic": "/SmartDashboard/# Has Coral",
              "period": 0.06,
              "data_type": "boolean",
              "true_color": 4293318731,
              "false_color": 4294198070,
              "true_icon": "None",
              "false_icon": "X"
            }
          },
          {
            "title": "# Algae Pickup",
            "x": 768.0,
            "y": 0.0,
            "width": 192.0,
            "height": 192.0,
            "type": "Boolean Box",
            "properties": {
              "topic": "/SmartDashboard/# Algae Pickup",
              "period": 0.06,
              "data_type": "boolean",
              "true_color": 4281911250,
              "false_color": 4294198070,
              "true_icon": "None",
              "false_icon": "X"
            }
          },
          {
            "title": "# Targeting Net",
            "x": 768.0,
            "y": 192.0,
            "width": 192.0,
            "height": 96.0,
            "type": "Boolean Box",
            "properties": {
              "topic": "/SmartDashboard/# Targeting Net",
              "period": 0.06,
              "data_type": "boolean",
              "true_color": 4283215696,
              "false_color": 4294198070,
              "true_icon": "None",
              "false_icon": "None"
            }
          },
          {
            "title": "Lock in auto program",
            "x": 0.0,
            "y": 0.0,
            "width": 192.0,
            "height": 192.0,
            "type": "ComboBox Chooser",
            "properties": {
              "topic": "/SmartDashboard/Lock in auto program",
              "period": 0.06,
              "sort_options": false
            }
          },
          {
            "title": "Select Autonomous Program",
            "x": 0.0,
            "y": 192.0,
            "width": 192.0,
            "height": 192.0,
            "type": "ComboBox Chooser",
            "properties": {
              "topic": "/SmartDashboard/Select Autonomous Program",
              "period": 0.06,
              "sort_options": false
            }
          },
          {
            "title": "# Targeting Processor",
            "x": 768.0,
            "y": 288.0,
            "width": 192.0,
            "height": 96.0,
            "type": "Boolean Box",
            "properties": {
              "topic": "/SmartDashboard/# Targeting Processor",
              "period": 0.06,
              "data_type": "boolean",
              "true_color": 4283215696,
              "false_color": 4294198070,
              "true_icon": "None",
              "false_icon": "None"
            }
          },
          {
            "title": "Gyro Reading",
            "x": 384.0,
            "y": 0.0,
            "width": 192.0,
            "height": 192.0,
            "type": "Text Display",
            "properties": {
              "topic": "/SmartDashboard/Gyro Reading",
              "period": 0.06,
              "data_type": "double",
              "show_submit_button": false
            }
          },
          {
            "title": "Preloaded Autonomous Program",
            "x": 0.0,
            "y": 384.0,
            "width": 384.0,
            "height": 96.0,
            "type": "Text Display",
            "properties": {
              "topic": "/SmartDashboard/Preloaded Autonomous Program",
              "period": 0.06,
              "data_type": "string",
              "show_submit_button": false
            }
          },
          {
            "title": "# Robot X",
            "x": 384.0,
            "y": 192.0,
            "width": 192.0,
            "height": 192.0,
            "type": "Text Display",
            "properties": {
              "topic": "/SmartDashboard/# Robot X",
              "period": 0.06,
              "data_type": "double",
              "show_submit_button": false
            }
          },
          {
            "title": "# Robot Y",
            "x": 576.0,
            "y": 192.0,
            "width": 192.0,
            "height": 192.0,
            "type": "Text Display",
            "properties": {
              "topic": "/SmartDashboard/# Robot Y",
              "period": 0.06,
              "data_type": "double",
              "show_submit_button": false
            }
          },
          {
            "title": "# climb ratchet on",
            "x": 960.0,
            "y": 384.0,
            "width": 192.0,
            "height": 96.0,
            "type": "Boolean Box",
            "properties": {
              "topic": "/SmartDashboard/# climb ratchet on",
              "period": 0.06,
              "data_type": "boolean",
              "true_color": 4283215696,
              "false_color": 4294198070,
              "true_icon": "None",
              "false_icon": "None"
            }
          },
          {
            "title": "# left branch",
            "x": 960.0,
            "y": 0.0,
            "width": 192.0,
            "height": 192.0,
            "type": "Boolean Box",
            "properties": {
              "topic": "/SmartDashboard/# left branch",
              "period": 0.06,
              "data_type": "boolean",
              "true_color": 4283215696,
              "false_color": 4294198070,
              "true_icon": "None",
              "false_icon": "None"
            }
          },
          {
            "title": "# right branch",
            "x": 1344.0,
            "y": 0.0,
            "width": 192.0,
            "height": 192.0,
            "type": "Boolean Box",
            "properties": {
              "topic": "/SmartDashboard/# right branch",
              "period": 0.06,
              "data_type": "boolean",
              "true_color": 4283215696,
              "false_color": 4294198070,
              "true_icon": "None",
              "false_icon": "None"
            }
          },
          {
            "title": "isBlue",
            "x": 192.0,
            "y": 192.0,
            "width": 192.0,
            "height": 192.0,
            "type": "Toggle Switch",
            "properties": {
              "topic": "/SmartDashboard/isBlue",
              "period": 0.06,
              "data_type": "boolean"
            }
          },
          {
            "title": "isBlue",
            "x": 192.0,
            "y": 0.0,
            "width": 192.0,
            "height": 192.0,
            "type": "Boolean Box",
            "properties": {
              "topic": "/SmartDashboard/isBlue",
              "period": 0.06,
              "data_type": "boolean",
              "true_color": 4280493032,
              "false_color": 4294198070,
              "true_icon": "None",
              "false_icon": "None"
            }
          }
        ]
      }
    },
    {
      "name": "Vision",
      "grid_layout": {
        "layouts": [],
        "containers": [
          {
            "title": "limelight-back",
            "x": 1152.0,
            "y": 0.0,
            "width": 384.0,
            "height": 384.0,
            "type": "Camera Stream",
            "properties": {
              "topic": "/CameraPublisher/limelight-back",
              "period": 0.06
            }
          },
          {
            "title": "# Robot X",
            "x": 768.0,
            "y": 0.0,
            "width": 192.0,
            "height": 192.0,
            "type": "Text Display",
            "properties": {
              "topic": "/SmartDashboard/# Robot X",
              "period": 0.06,
              "data_type": "double",
              "show_submit_button": false
            }
          },
          {
            "title": "# Robot Y",
            "x": 960.0,
            "y": 0.0,
            "width": 192.0,
            "height": 192.0,
            "type": "Text Display",
            "properties": {
              "topic": "/SmartDashboard/# Robot Y",
              "period": 0.06,
              "data_type": "double",
              "show_submit_button": false
            }
          },
          {
            "title": "Alliance Color",
            "x": 576.0,
            "y": 0.0,
            "width": 192.0,
            "height": 192.0,
            "type": "Boolean Box",
            "properties": {
              "topic": "/SmartDashboard/Alliance Color",
              "period": 0.06,
              "data_type": "boolean",
              "true_color": 4283215696,
              "false_color": 4294198070,
              "true_icon": "None",
              "false_icon": "None"
            }
          },
          {
            "title": "Drive mode",
            "x": 384.0,
            "y": 0.0,
            "width": 192.0,
            "height": 192.0,
            "type": "Text Display",
            "properties": {
              "topic": "/SmartDashboard/Drive mode",
              "period": 0.06,
              "data_type": "string",
              "show_submit_button": false
            }
          },
          {
            "title": "Gyro Reading",
            "x": 576.0,
            "y": 192.0,
            "width": 192.0,
            "height": 192.0,
            "type": "Text Display",
            "properties": {
              "topic": "/SmartDashboard/Gyro Reading",
              "period": 0.06,
              "data_type": "double",
              "show_submit_button": false
            }
          },
          {
            "title": "Rotation target",
            "x": 768.0,
            "y": 192.0,
            "width": 192.0,
            "height": 192.0,
            "type": "Text Display",
            "properties": {
              "topic": "/SmartDashboard/Rotation target",
              "period": 0.06,
              "data_type": "double",
              "show_submit_button": false
            }
          },
          {
            "title": "rotLocked",
            "x": 960.0,
            "y": 192.0,
            "width": 192.0,
            "height": 192.0,
            "type": "Boolean Box",
            "properties": {
              "topic": "/SmartDashboard/rotLocked",
              "period": 0.06,
              "data_type": "boolean",
              "true_color": 4283215696,
              "false_color": 4294198070,
              "true_icon": "None",
              "false_icon": "None"
            }
          },
          {
            "title": "botpose_orb_wpiblue",
            "x": 576.0,
            "y": 384.0,
            "width": 864.0,
            "height": 192.0,
            "type": "Text Display",
            "properties": {
              "topic": "/limelight-back/botpose_orb_wpiblue",
              "period": 0.06,
              "data_type": "double[]",
              "show_submit_button": false
            }
          },
          {
            "title": "@ is blue",
            "x": 384.0,
            "y": 192.0,
            "width": 192.0,
            "height": 192.0,
            "type": "Boolean Box",
            "properties": {
              "topic": "/SmartDashboard/@ is blue",
              "period": 0.06,
              "data_type": "boolean",
              "true_color": 4283215696,
              "false_color": 4294198070,
              "true_icon": "None",
              "false_icon": "None"
            }
          },
          {
            "title": "Lock in auto program",
            "x": 192.0,
            "y": 192.0,
            "width": 192.0,
            "height": 192.0,
            "type": "ComboBox Chooser",
            "properties": {
              "topic": "/SmartDashboard/Lock in auto program",
              "period": 0.06,
              "sort_options": false
            }
          },
          {
            "title": "Select Autonomous Program",
            "x": 192.0,
            "y": 0.0,
            "width": 192.0,
            "height": 192.0,
            "type": "ComboBox Chooser",
            "properties": {
              "topic": "/SmartDashboard/Select Autonomous Program",
              "period": 0.06,
              "sort_options": false
            }
          }
        ]
      }
    }
  ]
}